gunlink/__init__.py
gunlink/gunlink.py
gunlink/core/__init__.py
gunlink/core/errors.py
gunlink/core/funtions.py
gunlink/core/subclass.py
gunlink-1.0.1.dist-info/LICENSE.txt
gunlink-1.0.1.dist-info/METADATA
gunlink-1.0.1.dist-info/WHEEL
gunlink-1.0.1.dist-info/top_level.txt
gunlink-1.0.1.dist-info/RECORD
