Metadata-Version: 2.1
Name: gunlink
Version: 1.0.1
Summary: Handling links
Home-page: https://github.com/Brijeshkrishna/gunlink
Author: Brijesh Krishna
Author-email: brijeshkrishnaga@gmail.com
License: MIT
Keywords: gunlink,python,link,python3
Platform: UNKNOWN
Classifier: Intended Audience :: Developers
Classifier: Programming Language :: Python :: 3
Classifier: Operating System :: Unix
Classifier: Operating System :: MacOS :: MacOS X
Classifier: Operating System :: Microsoft :: Windows
Requires-Dist: numpy
Requires-Dist: ipwhois
Requires-Dist: pyshorteners
Requires-Dist: pydantic
